{
  "agentRetries": {
    "256293": {
      "failureCount": 28,
      "lastAttemptAt": "2026-07-08T00:09:49.433826Z",
      "lastAttemptRun": 55,
      "lastFailedReason": "A:avatar_added_false,B:parse:no_agent_card_div"
    },
    "272165": {
      "failureCount": 28,
      "lastAttemptAt": "2026-07-08T00:09:44.380166Z",
      "lastAttemptRun": 55,
      "lastFailedReason": "A:avatar_added_false,B:parse:no_agent_card_div"
    },
    "272187": {
      "failureCount": 28,
      "lastAttemptAt": "2026-07-08T00:09:46.907969Z",
      "lastAttemptRun": 55,
      "lastFailedReason": "A:avatar_added_false,B:parse:no_agent_card_div"
    },
    "272239": {
      "failureCount": 28,
      "lastAttemptAt": "2026-07-08T00:09:48.169459Z",
      "lastAttemptRun": 55,
      "lastFailedReason": "A:avatar_added_false,B:parse:no_agent_card_div"
    },
    "272264": {
      "failureCount": 28,
      "lastAttemptAt": "2026-07-08T00:09:50.711633Z",
      "lastAttemptRun": 55,
      "lastFailedReason": "A:avatar_added_false,B:parse:no_agent_card_div"
    },
    "272268": {
      "failureCount": 28,
      "lastAttemptAt": "2026-07-08T00:09:51.980798Z",
      "lastAttemptRun": 55,
      "lastFailedReason": "A:avatar_added_false,B:parse:no_agent_card_div"
    },
    "272272": {
      "failureCount": 28,
      "lastAttemptAt": "2026-07-08T00:09:45.626119Z",
      "lastAttemptRun": 55,
      "lastFailedReason": "A:avatar_added_false,B:parse:no_agent_card_div"
    },
    "272295": {
      "failureCount": 28,
      "lastAttemptAt": "2026-07-08T00:09:55.679356Z",
      "lastAttemptRun": 55,
      "lastFailedReason": "A:avatar_added_false,B:parse:no_agent_card_div"
    },
    "272299": {
      "failureCount": 28,
      "lastAttemptAt": "2026-07-08T00:09:56.903467Z",
      "lastAttemptRun": 55,
      "lastFailedReason": "A:avatar_added_false,B:parse:no_agent_card_div"
    },
    "272337": {
      "failureCount": 28,
      "lastAttemptAt": "2026-07-08T00:09:58.130494Z",
      "lastAttemptRun": 55,
      "lastFailedReason": "A:avatar_added_false,B:parse:no_agent_card_div"
    },
    "272373": {
      "failureCount": 28,
      "lastAttemptAt": "2026-07-08T00:09:59.377439Z",
      "lastAttemptRun": 55,
      "lastFailedReason": "A:avatar_added_false,B:parse:no_agent_card_div"
    },
    "272387": {
      "failureCount": 28,
      "lastAttemptAt": "2026-07-08T00:10:01.855738Z",
      "lastAttemptRun": 55,
      "lastFailedReason": "A:avatar_added_false,B:parse:no_agent_card_div"
    },
    "272401": {
      "failureCount": 28,
      "lastAttemptAt": "2026-07-08T00:10:04.288174Z",
      "lastAttemptRun": 55,
      "lastFailedReason": "A:avatar_added_false,B:parse:no_agent_card_div"
    },
    "272405": {
      "failureCount": 28,
      "lastAttemptAt": "2026-07-08T00:10:08.006745Z",
      "lastAttemptRun": 55,
      "lastFailedReason": "A:avatar_added_false,B:parse:no_agent_card_div"
    },
    "272578": {
      "failureCount": 28,
      "lastAttemptAt": "2026-07-08T00:10:05.522680Z",
      "lastAttemptRun": 55,
      "lastFailedReason": "A:avatar_added_false,B:parse:no_agent_card_div"
    },
    "277381": {
      "failureCount": 28,
      "lastAttemptAt": "2026-07-08T00:09:54.452519Z",
      "lastAttemptRun": 55,
      "lastFailedReason": "A:avatar_added_false,B:parse:no_agent_card_div"
    },
    "299771": {
      "failureCount": 28,
      "lastAttemptAt": "2026-07-08T00:10:00.595557Z",
      "lastAttemptRun": 55,
      "lastFailedReason": "A:avatar_added_false,B:parse:no_agent_card_div"
    },
    "300610": {
      "failureCount": 28,
      "lastAttemptAt": "2026-07-08T00:10:03.066270Z",
      "lastAttemptRun": 55,
      "lastFailedReason": "A:avatar_added_false,B:parse:no_agent_card_div"
    },
    "302753": {
      "failureCount": 22,
      "lastAttemptAt": "2026-07-08T00:09:53.247529Z",
      "lastAttemptRun": 55,
      "lastFailedReason": "A:avatar_added_false,B:parse:no_agent_card_div"
    },
    "303292": {
      "failureCount": 17,
      "lastAttemptAt": "2026-07-08T00:10:06.744184Z",
      "lastAttemptRun": 55,
      "lastFailedReason": "A:avatar_added_false,B:parse:no_agent_card_div"
    },
    "303648": {
      "failureCount": 12,
      "lastAttemptAt": "2026-07-08T15:31:07.092712Z",
      "lastAttemptRun": 56,
      "lastFailedReason": "A:avatar_added_false,B:parse:no_agent_card_div"
    }
  },
  "runCounter": 56
}