{
  "generated": "2026-05-18T15:00:39.356796",
  "dry_run": false,
  "description": "Agents on site with no profile photo. Add a photo in Lofty (preferred) or BoldTrail to populate.",
  "count": 49,
  "agents": [
    {
      "name": "Aaron Kroggel",
      "email": "aaron@glasshouserealty.com",
      "regions": [
        "Dayton"
      ],
      "team": "",
      "source": "boldtrail",
      "boldtrailId": "272164",
      "loftyId": ""
    },
    {
      "name": "Adam Bauer",
      "email": "adam.bauer77@gmail.com",
      "regions": [
        "Dayton"
      ],
      "team": "",
      "source": "boldtrail",
      "boldtrailId": "272165",
      "loftyId": ""
    },
    {
      "name": "Anna Catanzaro",
      "email": "ohiohomegirls@gmail.com",
      "regions": [
        "Dayton",
        "Columbus"
      ],
      "team": "",
      "source": "boldtrail",
      "boldtrailId": "272178",
      "loftyId": ""
    },
    {
      "name": "Bobby Hopkins",
      "email": "bobby@glasshouserealty.com",
      "regions": [
        "Dayton"
      ],
      "team": "",
      "source": "boldtrail",
      "boldtrailId": "285335",
      "loftyId": ""
    },
    {
      "name": "Brian Budde",
      "email": "buddebrian@gmail.com",
      "regions": [
        "Cincinnati"
      ],
      "team": "",
      "source": "boldtrail",
      "boldtrailId": "272187",
      "loftyId": ""
    },
    {
      "name": "Brittany Singer",
      "email": "brittanysinger.gh@outlook.com",
      "regions": [
        "Dayton",
        "Cincinnati"
      ],
      "team": "LUX Elite Group",
      "source": "boldtrail",
      "boldtrailId": "275114",
      "loftyId": ""
    },
    {
      "name": "Cortney Loyd",
      "email": "loyd.cortney@gmail.com",
      "regions": [
        "Dayton"
      ],
      "team": "",
      "source": "boldtrail",
      "boldtrailId": "272214",
      "loftyId": ""
    },
    {
      "name": "Danaisha Tate",
      "email": "dtate_realestate@yahoo.com",
      "regions": [
        "Dayton"
      ],
      "team": "",
      "source": "boldtrail",
      "boldtrailId": "278010",
      "loftyId": ""
    },
    {
      "name": "David Jenks",
      "email": "info@davidjenks.com",
      "regions": [
        "Dayton"
      ],
      "team": "",
      "source": "boldtrail",
      "boldtrailId": "272225",
      "loftyId": ""
    },
    {
      "name": "David Woodward",
      "email": "david@glasshouserealty.com",
      "regions": [
        "Dayton"
      ],
      "team": "",
      "source": "boldtrail",
      "boldtrailId": "272226",
      "loftyId": ""
    },
    {
      "name": "Eric Loudenback",
      "email": "eloudenback@gmail.com",
      "regions": [
        "Dayton"
      ],
      "team": "",
      "source": "boldtrail",
      "boldtrailId": "272239",
      "loftyId": ""
    },
    {
      "name": "Erika Deady",
      "email": "eadeady5@gmail.com",
      "regions": [
        "Dayton"
      ],
      "team": "",
      "source": "boldtrail",
      "boldtrailId": "277366",
      "loftyId": ""
    },
    {
      "name": "Hailey Cox",
      "email": "haileycox2004@gmail.com",
      "regions": [
        "Dayton"
      ],
      "team": "Cox Team (Placeholder)",
      "source": "boldtrail",
      "boldtrailId": "275089",
      "loftyId": ""
    },
    {
      "name": "Harley Wade",
      "email": "harley@glasshouserealty.com",
      "regions": [
        "Dayton"
      ],
      "team": "",
      "source": "boldtrail",
      "boldtrailId": "272245",
      "loftyId": ""
    },
    {
      "name": "Hayley Stewart",
      "email": "hayley@glasshouserealty.com",
      "regions": [
        "Dayton"
      ],
      "team": "",
      "source": "boldtrail",
      "boldtrailId": "272246",
      "loftyId": ""
    },
    {
      "name": "Jayvon Tate",
      "email": "jayvon_tate@glasshouserealty.com",
      "regions": [
        "Dayton"
      ],
      "team": "",
      "source": "boldtrail",
      "boldtrailId": "278681",
      "loftyId": ""
    },
    {
      "name": "Jennifer Martinez",
      "email": "soldbyjenniferm@gmail.com",
      "regions": [
        "Dayton"
      ],
      "team": "Dayton Real Estate Crush",
      "source": "boldtrail",
      "boldtrailId": "272263",
      "loftyId": ""
    },
    {
      "name": "Jeri Baumann",
      "email": "jeri@glasshouserealty.com",
      "regions": [
        "Dayton"
      ],
      "team": "",
      "source": "boldtrail",
      "boldtrailId": "272264",
      "loftyId": ""
    },
    {
      "name": "Jill Barhorst",
      "email": "jillbsellshouses@gmail.com",
      "regions": [
        "Dayton"
      ],
      "team": "",
      "source": "boldtrail",
      "boldtrailId": "272268",
      "loftyId": ""
    },
    {
      "name": "Joseph Zaharieff",
      "email": "j.alexz@outlook.com",
      "regions": [
        "Dayton"
      ],
      "team": "K4 Management Group",
      "source": "boldtrail",
      "boldtrailId": "272272",
      "loftyId": ""
    },
    {
      "name": "Kaitlyn Perkins",
      "email": "kaitlyn.perkins@glasshouserealty.com",
      "regions": [
        "Dayton"
      ],
      "team": "",
      "source": "boldtrail",
      "boldtrailId": "295578",
      "loftyId": ""
    },
    {
      "name": "Kasey Prikkel",
      "email": "kaseyprikkelrealestate@gmail.com",
      "regions": [
        "Dayton"
      ],
      "team": "",
      "source": "boldtrail",
      "boldtrailId": "272281",
      "loftyId": ""
    },
    {
      "name": "Keith Gabbard",
      "email": "keithgabbard.1@gmail.com",
      "regions": [
        "Dayton",
        "Cincinnati"
      ],
      "team": "",
      "source": "boldtrail",
      "boldtrailId": "277381",
      "loftyId": ""
    },
    {
      "name": "Kerry Phillips",
      "email": "kerry@movewithkerry.com",
      "regions": [
        "Dayton"
      ],
      "team": "",
      "source": "boldtrail",
      "boldtrailId": "272289",
      "loftyId": ""
    },
    {
      "name": "Kimberly Luehmann",
      "email": "kimberlyl@glasshouserealty.com",
      "regions": [
        "Dayton"
      ],
      "team": "",
      "source": "boldtrail",
      "boldtrailId": "272295",
      "loftyId": ""
    },
    {
      "name": "Kristine Bertrand",
      "email": "onerealvalue@gmail.com",
      "regions": [
        "Dayton"
      ],
      "team": "",
      "source": "boldtrail",
      "boldtrailId": "272299",
      "loftyId": ""
    },
    {
      "name": "Kunal Patel",
      "email": "kunal@kunalpatelgroup.com",
      "regions": [
        "Dayton"
      ],
      "team": "Kunal Patel Group",
      "source": "boldtrail",
      "boldtrailId": "272300",
      "loftyId": ""
    },
    {
      "name": "Kyle Ward",
      "email": "kyle.asacoxhomes@gmail.com",
      "regions": [
        "Cleveland"
      ],
      "team": "",
      "source": "boldtrail-cleveland",
      "boldtrailId": "293457",
      "loftyId": ""
    },
    {
      "name": "Lacey Watson",
      "email": "laceywatsonre@gmail.com",
      "regions": [
        "Dayton"
      ],
      "team": "",
      "source": "boldtrail",
      "boldtrailId": "272302",
      "loftyId": ""
    },
    {
      "name": "Lauren Galdeen",
      "email": "listwithlaurengaldeen@gmail.com",
      "regions": [
        "Dayton"
      ],
      "team": "",
      "source": "boldtrail",
      "boldtrailId": "272305",
      "loftyId": ""
    },
    {
      "name": "Lauren Rau",
      "email": "laurenraucre@gmail.com",
      "regions": [
        "Dayton"
      ],
      "team": "",
      "source": "boldtrail",
      "boldtrailId": "297951",
      "loftyId": ""
    },
    {
      "name": "Madison Justice",
      "email": "madison@navehometeam.com",
      "regions": [
        "Dayton",
        "Columbus"
      ],
      "team": "Nave Home Team",
      "source": "boldtrail",
      "boldtrailId": "272316",
      "loftyId": ""
    },
    {
      "name": "Mary Johnson",
      "email": "maryjrealtor@gmail.com",
      "regions": [
        "Cleveland"
      ],
      "team": "",
      "source": "boldtrail-cleveland",
      "boldtrailId": "294696",
      "loftyId": ""
    },
    {
      "name": "Michael Williams",
      "email": "mike@cornerstonevetclinic.com",
      "regions": [
        "Dayton"
      ],
      "team": "",
      "source": "boldtrail",
      "boldtrailId": "272337",
      "loftyId": ""
    },
    {
      "name": "Misty Vincent",
      "email": "misty@glasshouserealty.com",
      "regions": [
        "Dayton"
      ],
      "team": "",
      "source": "boldtrail",
      "boldtrailId": "297995",
      "loftyId": ""
    },
    {
      "name": "Rachel Dunham",
      "email": "rachel.dunham1@aim.com",
      "regions": [
        "Dayton"
      ],
      "team": "Tru Integrity Group",
      "source": "boldtrail",
      "boldtrailId": "272360",
      "loftyId": ""
    },
    {
      "name": "Reena Patel",
      "email": "reenapatelrealty@gmail.com",
      "regions": [
        "Dayton"
      ],
      "team": "",
      "source": "boldtrail",
      "boldtrailId": "272364",
      "loftyId": ""
    },
    {
      "name": "Richard Kloth",
      "email": "evan@z-kgroup.com",
      "regions": [
        "Dayton"
      ],
      "team": "Zahedi Kloth Group",
      "source": "boldtrail",
      "boldtrailId": "256293",
      "loftyId": ""
    },
    {
      "name": "Rosario Torres Bermudez",
      "email": "rrealtorrosario@gmail.com",
      "regions": [
        "Cleveland"
      ],
      "team": "Alyssa Christison Team",
      "source": "boldtrail-cleveland",
      "boldtrailId": "295320",
      "loftyId": ""
    },
    {
      "name": "Samantha Tschida",
      "email": "chasewithtschida@gmail.com",
      "regions": [
        "Dayton",
        "Columbus"
      ],
      "team": "",
      "source": "boldtrail",
      "boldtrailId": "272373",
      "loftyId": ""
    },
    {
      "name": "Scottie Fulhart",
      "email": "soldwithscottie@gmail.com",
      "regions": [
        "Dayton"
      ],
      "team": "",
      "source": "boldtrail",
      "boldtrailId": "296298",
      "loftyId": ""
    },
    {
      "name": "Sophia Luza",
      "email": "snluza9@gmail.com",
      "regions": [
        "Dayton"
      ],
      "team": "",
      "source": "boldtrail",
      "boldtrailId": "272387",
      "loftyId": ""
    },
    {
      "name": "Stephanie Wunderlich",
      "email": "stephanie.t@glasshouserealty.com",
      "regions": [
        "Dayton"
      ],
      "team": "",
      "source": "boldtrail",
      "boldtrailId": "272389",
      "loftyId": ""
    },
    {
      "name": "Susan Marra",
      "email": "smarra@glasshouserealty.com",
      "regions": [
        "Dayton"
      ],
      "team": "",
      "source": "boldtrail",
      "boldtrailId": "272395",
      "loftyId": ""
    },
    {
      "name": "Teresa Hobbs",
      "email": "teri@glasshouserealty.com",
      "regions": [
        "Dayton"
      ],
      "team": "",
      "source": "boldtrail",
      "boldtrailId": "272401",
      "loftyId": ""
    },
    {
      "name": "Thomas Kretz",
      "email": "thomas.j.kretz@gmail.com",
      "regions": [
        "Dayton"
      ],
      "team": "K4 Management Group",
      "source": "boldtrail",
      "boldtrailId": "272405",
      "loftyId": ""
    },
    {
      "name": "Tia Turner",
      "email": "tia@glasshouserealty.com",
      "regions": [
        "Dayton"
      ],
      "team": "",
      "source": "boldtrail",
      "boldtrailId": "272578",
      "loftyId": ""
    },
    {
      "name": "Tracey Tanner",
      "email": "buysellohio@keyswithtracey.com",
      "regions": [
        "Dayton"
      ],
      "team": "",
      "source": "boldtrail",
      "boldtrailId": "296320",
      "loftyId": ""
    },
    {
      "name": "Zachary Banks",
      "email": "zac@goodguyteam.com",
      "regions": [
        "Dayton"
      ],
      "team": "Good Guy Group",
      "source": "boldtrail",
      "boldtrailId": "272590",
      "loftyId": ""
    }
  ]
}